claude_smalltalk/__init__.py
claude_smalltalk/mcp_server.py
claude_smalltalk/openai_mcp.py
claude_smalltalk/openai_tools.py
claude_smalltalk-1.2.2.dist-info/METADATA
claude_smalltalk-1.2.2.dist-info/WHEEL
claude_smalltalk-1.2.2.dist-info/entry_points.txt
claude_smalltalk-1.2.2.dist-info/licenses/LICENSE
claude_smalltalk-1.2.2.dist-info/licenses/LICENSE-CUIS
claude_smalltalk-1.2.2.dist-info/licenses/LICENSE-MQTT
claude_smalltalk-1.2.2.dist-info/RECORD
