Metadata-Version: 2.4
Name: claude-smalltalk
Version: 1.2.2
Summary: MCP server for AI interaction with live Smalltalk images (Cuis and Squeak)
Project-URL: Homepage, https://github.com/CorporateSmalltalkConsultingLtd/ClaudeSmalltalk
Project-URL: Repository, https://github.com/CorporateSmalltalkConsultingLtd/ClaudeSmalltalk
Author: Corporate Smalltalk Consulting Ltd
License: MIT
License-File: LICENSE
License-File: LICENSE-CUIS
License-File: LICENSE-MQTT
Keywords: ai,claude,cuis,llm,mcp,model-context-protocol,openai,smalltalk,squeak
Classifier: Development Status :: 4 - Beta
Classifier: Intended Audience :: Developers
Classifier: License :: OSI Approved :: MIT License
Classifier: Programming Language :: Python :: 3
Classifier: Programming Language :: Python :: 3.10
Classifier: Programming Language :: Python :: 3.11
Classifier: Programming Language :: Python :: 3.12
Classifier: Topic :: Scientific/Engineering :: Artificial Intelligence
Classifier: Topic :: Software Development :: Interpreters
Requires-Python: >=3.10
Requires-Dist: mcp>=1.0.0
Requires-Dist: paho-mqtt>=2.0.0
Provides-Extra: all
Requires-Dist: openai>=1.0.0; extra == 'all'
Provides-Extra: openai
Requires-Dist: openai>=1.0.0; extra == 'openai'
